imdb_search/__init__.py
imdb_search/main.py
imdb_search-1.0.0.dist-info/LICENSE
imdb_search-1.0.0.dist-info/METADATA
imdb_search-1.0.0.dist-info/WHEEL
imdb_search-1.0.0.dist-info/entry_points.txt
imdb_search-1.0.0.dist-info/top_level.txt
imdb_search-1.0.0.dist-info/RECORD
