Metadata-Version: 2.1
Name: imdb-search
Version: 1.0.0
Summary: CLI to search for movies than an actor/actress has starred in.
Home-page: https://github.com/richardfontein/imdb-search
Author: Richard Fontein
Author-email: richard@fontein.co
License: MIT
Platform: UNKNOWN
Classifier: Programming Language :: Python :: 3
Classifier: License :: OSI Approved :: MIT License
Classifier: Operating System :: OS Independent
Requires-Python: >=3
Requires-Dist: pick
Requires-Dist: requests
